slavko_package/__init__.py
slavko_package/package_1.py
slavko_package-0.0.1.dist-info/LICENSE
slavko_package-0.0.1.dist-info/METADATA
slavko_package-0.0.1.dist-info/WHEEL
slavko_package-0.0.1.dist-info/top_level.txt
slavko_package-0.0.1.dist-info/RECORD
