Metadata-Version: 2.1
Name: slavko-package
Version: 0.0.1
License-File: LICENSE
Requires-Dist: requests
Requires-Dist: importlib-metadata ; python_version == "3.8"
